storages/__init__.py
storages/base.py
storages/compress.py
storages/utils.py
storages/backends/__init__.py
storages/backends/apache_libcloud.py
storages/backends/azure_storage.py
storages/backends/dropbox.py
storages/backends/ftp.py
storages/backends/gcloud.py
storages/backends/ibm_cos.py
storages/backends/s3boto3.py
storages/backends/sftpstorage.py
actinis_django_storages-1.12.6.dist-info/AUTHORS
actinis_django_storages-1.12.6.dist-info/LICENSE
actinis_django_storages-1.12.6.dist-info/METADATA
actinis_django_storages-1.12.6.dist-info/WHEEL
actinis_django_storages-1.12.6.dist-info/top_level.txt
actinis_django_storages-1.12.6.dist-info/RECORD
