Metadata-Version: 2.1
Name: actinis-django-storages
Version: 1.12.6
Summary: Same as django-storages, but with IBM COS support
Home-page: https://github.com/Actinis/django-storages
Author: Josh Schneier / Ajay Shah / Fork: Artem Smirnov
Author-email: artem@actinis.io
License: BSD-3-Clause
Classifier: Development Status :: 5 - Production/Stable
Classifier: Environment :: Web Environment
Classifier: Framework :: Django
Classifier: Framework :: Django :: 2.2
Classifier: Framework :: Django :: 3.0
Classifier: Framework :: Django :: 3.1
Classifier: Framework :: Django :: 3.2
Classifier: Intended Audience :: Developers
Classifier: License :: OSI Approved :: BSD License
Classifier: Operating System :: OS Independent
Classifier: Programming Language :: Python
Classifier: Programming Language :: Python :: 3
Classifier: Programming Language :: Python :: 3 :: Only
Classifier: Programming Language :: Python :: 3.5
Classifier: Programming Language :: Python :: 3.6
Classifier: Programming Language :: Python :: 3.7
Classifier: Programming Language :: Python :: 3.8
Classifier: Programming Language :: Python :: 3.9
Classifier: Programming Language :: Python :: 3.10
Requires-Python: >=3.5
License-File: LICENSE
License-File: AUTHORS
Requires-Dist: Django (>=2.2)
Provides-Extra: azure
Requires-Dist: azure-storage-blob (>=12.0.0) ; extra == 'azure'
Provides-Extra: boto3
Requires-Dist: boto3 (>=1.4.4) ; extra == 'boto3'
Provides-Extra: dropbox
Requires-Dist: dropbox (>=7.2.1) ; extra == 'dropbox'
Provides-Extra: google
Requires-Dist: google-cloud-storage (>=1.27.0) ; extra == 'google'
Provides-Extra: libcloud
Requires-Dist: apache-libcloud ; extra == 'libcloud'
Provides-Extra: sftp
Requires-Dist: paramiko ; extra == 'sftp'
